pmsh/__init__.py
pmsh/detect.py
pmsh/pmsh_ocr.py
pmsh/recognize.py
pmsh/tokenize.py
pmsh/models/decoder_loop.onnx
pmsh/models/encoder_ctc.onnx
pmsh_ocr-0.0.1.dist-info/LICENSE
pmsh_ocr-0.0.1.dist-info/METADATA
pmsh_ocr-0.0.1.dist-info/WHEEL
pmsh_ocr-0.0.1.dist-info/top_level.txt
pmsh_ocr-0.0.1.dist-info/RECORD
