Metadata-Version: 2.2
Name: pmsh-ocr
Version: 0.0.1
Summary: Primary Math Screen Handwriting OCR (pmsh-ocr) is a Python package for recognizing primary mathematical expressions handwritten on screen.
Author-email: Martin HM MaDing <mading5@xdf.cn>
License: MIT
Project-URL: Homepage, https://github.com/yourusername/pmsh-ocr
Keywords: Primary Math,Screen Handwriting,OCR
Classifier: Programming Language :: Python :: 3
Classifier: License :: OSI Approved :: MIT License
Classifier: Operating System :: OS Independent
Requires-Python: >=3.9
License-File: LICENSE
Requires-Dist: opencv-python
Requires-Dist: numpy
Requires-Dist: onnxruntime
